<annotation verified="yes">
    <folder>Annotation</folder>
    <filename>20.09.17_13.jpg</filename>
    <path>20.09.30.annotation-PascalVOC-export/Annotations/20.09.17_13.jpg</path>
    <source>
        <database>Unknown</database>
    </source>
    <size>
        <width>1500</width>
        <height>266</height>
        <depth>3</depth>
    </size>
    <segmented>0</segmented>
    <object>
    <name>difficult_person</name>
    <pose>Unspecified</pose>
    <truncated>0</truncated>
    <difficult>0</difficult>
    <bndbox>
        <xmin>382.05499276410995</xmin>
        <ymin>134.13660714285714</ymin>
        <xmax>393.9942112879884</xmax>
        <ymax>156.93660714285716</ymax>
    </bndbox>
</object>
</annotation>
