<annotation verified="yes">
    <folder>Annotation</folder>
    <filename>20.09.17_31.jpg</filename>
    <path>20.09.30.annotation-PascalVOC-export/Annotations/20.09.17_31.jpg</path>
    <source>
        <database>Unknown</database>
    </source>
    <size>
        <width>1500</width>
        <height>266</height>
        <depth>3</depth>
    </size>
    <segmented>0</segmented>
    <object>
    <name>difficult_person</name>
    <pose>Unspecified</pose>
    <truncated>0</truncated>
    <difficult>0</difficult>
    <bndbox>
        <xmin>396.1649782923299</xmin>
        <ymin>143.90803571428572</ymin>
        <xmax>405.9334298118668</xmax>
        <ymax>166.7080357142857</ymax>
    </bndbox>
</object>
</annotation>
